py2sqlm/__init__.py
py2sqlm/fields.py
py2sqlm/table.py
py2sqlm/utils.py
py2sqlm_andlvovsky-1.0.1.dist-info/METADATA
py2sqlm_andlvovsky-1.0.1.dist-info/WHEEL
py2sqlm_andlvovsky-1.0.1.dist-info/top_level.txt
py2sqlm_andlvovsky-1.0.1.dist-info/RECORD
